adsb/__init__.py
adsb/aircraft_db.py
adsb/api.py
adsb/cli.py
adsb/database.py
adsb/decoder.py
adsb/models.py
adsb/network.py
adsb/schemas.py
adsb_map-0.1.1.dist-info/METADATA
adsb_map-0.1.1.dist-info/WHEEL
adsb_map-0.1.1.dist-info/entry_points.txt
adsb_map-0.1.1.dist-info/licenses/LICENSE
adsb_map-0.1.1.dist-info/RECORD
