Metadata-Version: 2.4
Name: adsb-map
Version: 0.1.1
Summary: Python library for ADS-B decoding and REST API using pyModeS
Project-URL: Homepage, https://github.com/jbencina/adsb
Project-URL: Repository, https://github.com/jbencina/adsb
Project-URL: Issues, https://github.com/jbencina/adsb/issues
Author-email: John Bencina <jbencina@users.noreply.github.com>
License: GPL-3.0-or-later
License-File: LICENSE
Keywords: ads-b,adsb,aircraft,aviation,beast,decoder,mode-s,pymodes,sdr,tracking
Classifier: Development Status :: 4 - Beta
Classifier: Environment :: Console
Classifier: Environment :: Web Environment
Classifier: Framework :: FastAPI
Classifier: Intended Audience :: Developers
Classifier: Intended Audience :: Science/Research
Classifier: License :: OSI Approved :: GNU General Public License v3 or later (GPLv3+)
Classifier: Operating System :: OS Independent
Classifier: Programming Language :: Python :: 3
Classifier: Programming Language :: Python :: 3 :: Only
Classifier: Programming Language :: Python :: 3.12
Classifier: Programming Language :: Python :: 3.13
Classifier: Topic :: Scientific/Engineering
Classifier: Topic :: Scientific/Engineering :: Information Analysis
Classifier: Topic :: System :: Monitoring
Requires-Python: >=3.12
Requires-Dist: click>=8.1.0
Requires-Dist: fastapi>=0.115.0
Requires-Dist: pydantic>=2.9.0
Requires-Dist: pymodes>=2.21.0
Requires-Dist: sqlalchemy>=2.0.0
Requires-Dist: uvicorn[standard]>=0.30.0
